cinewiz/__init__.py
cinewiz/example.py
cinewiz/genai.py
cinewiz/web.py
cinewiz-2.0.dist-info/licenses/LICENSE.txt
cinewiz-2.0.dist-info/METADATA
cinewiz-2.0.dist-info/WHEEL
cinewiz-2.0.dist-info/top_level.txt
cinewiz-2.0.dist-info/RECORD
