Metadata-Version: 2.4
Name: cinewiz
Version: 2.0
Summary: **Cinewiz** is an open-source Python package designed to streamline the development of **multimodal applications** powered by **LLMs**, **RAG (Retrieval-Augmented Generation)**, and **web crawling**. It’s built for workflows that require dynamic content generation and automation in creative environments.
Home-page: https://github.com/ssmool/cinewiz
Author: #ASYTRICK
Author-email: eusmool@gmail.com
Classifier: Programming Language :: Python :: 3
Classifier: Operating System :: OS Independent
Classifier: Development Status :: 4 - Beta
Requires-Python: >=3.0
License-File: LICENSE.txt
Requires-Dist: rembg
Requires-Dist: Pillow
Requires-Dist: qrcode
Requires-Dist: selenium
Requires-Dist: webdriver_manager
Requires-Dist: transformers
Requires-Dist: opencv-python
Requires-Dist: numpy
Requires-Dist: scikit-image
Dynamic: license-file
